{
  "maj": "2026-07-22T16:56:51.948587+00:00",
  "kill_switch": false,
  "equity": 9938.7,
  "cash": 3266.62,
  "perf_jour_pct": -0.24,
  "positions": [
    {
      "symbole": "AAPL",
      "valeur": 635.27,
      "pnl_pct": -0.05
    },
    {
      "symbole": "AMD",
      "valeur": 326.01,
      "pnl_pct": 0.07
    },
    {
      "symbole": "CAT",
      "valeur": 462.1,
      "pnl_pct": -0.22
    },
    {
      "symbole": "JPM",
      "valeur": 1178.95,
      "pnl_pct": 0.28
    },
    {
      "symbole": "QQQ",
      "valeur": 1049.33,
      "pnl_pct": -0.04
    },
    {
      "symbole": "SPY",
      "valeur": 1193.18,
      "pnl_pct": 0.09
    },
    {
      "symbole": "UNH",
      "valeur": 850.01,
      "pnl_pct": -0.15
    },
    {
      "symbole": "V",
      "valeur": 977.23,
      "pnl_pct": 0.3
    }
  ],
  "cibles": [
    "AMD",
    "UNH",
    "SPY",
    "JPM",
    "AAPL",
    "V",
    "QQQ",
    "CAT"
  ]
}